setup.py
easycircle/__init__.py
easycircle/mianji.py
easycircle/zhouchang.py
easycircle.egg-info/PKG-INFO
easycircle.egg-info/SOURCES.txt
easycircle.egg-info/dependency_links.txt
easycircle.egg-info/top_level.txt