Metadata-Version: 1.0
Name: easycircle
Version: 0.1.0
Summary: Make circle easy!
Home-page: UNKNOWN
Author: Jiang Liu
Author-email: 3457266634@qq.com
License: MIT License
Keywords: a
Platform: any
